{
  "type": "Feature",
  "geometry": {
    "type": "Point",
    "coordinates": [
      -113.783,
      44.1333
    ]
  },
  "properties": {
    "name": "Borah Peak (Mount Borah)",
    "latitude": 44.1333,
    "longitude": -113.783,
    "feet": 12662,
    "meters": 3859,
    "continent": "North America",
    "country": "United States",
    "state": "Idaho"
  }
}
