{
  "type": "Feature",
  "geometry": {
    "type": "Point",
    "coordinates": [
      -114.175,
      43.4802
    ]
  },
  "properties": {
    "name": "Rock Roll Peak",
    "latitude": 43.4802,
    "longitude": -114.175,
    "feet": 10458,
    "meters": 3188,
    "continent": "North America",
    "country": "United States",
    "state": "Idaho"
  }
}
