{
  "type": "Feature",
  "geometry": {
    "type": "Point",
    "coordinates": [
      -113.81,
      43.6997
    ]
  },
  "properties": {
    "name": "Smiley Mountain",
    "latitude": 43.6997,
    "longitude": -113.81,
    "feet": 11508,
    "meters": 3508,
    "continent": "North America",
    "country": "United States",
    "state": "Idaho",
    "marker-symbol": "triangle",
    "marker-size": "small"
  }
}
