{
  "type": "Feature",
  "geometry": {
    "type": "Point",
    "coordinates": [
      20.546667,
      41.790278
    ]
  },
  "properties": {
    "name": "Golem Korab",
    "latitude": 41.790278,
    "longitude": 20.546667,
    "feet": 9068,
    "meters": 2764,
    "continent": "Europe",
    "country": "Macedonia/Albania"
  }
}
