{
  "type": "Feature",
  "geometry": {
    "type": "Point",
    "coordinates": [
      -148.966572,
      61.622832
    ]
  },
  "properties": {
    "name": "Lazy Mountain",
    "latitude": 61.622832,
    "longitude": -148.966572,
    "feet": 3763,
    "meters": 1147,
    "continent": "North America",
    "country": "United States",
    "state": "Alaska"
  }
}
