{
  "type": "Feature",
  "geometry": {
    "type": "Point",
    "coordinates": [
      -150.611,
      62.97
    ]
  },
  "properties": {
    "name": "Moose's Tooth",
    "latitude": 62.97,
    "longitude": -150.611,
    "feet": 10335,
    "meters": 3150,
    "continent": "North America",
    "country": "United States",
    "state": "Alaska"
  }
}
