{
  "type": "Feature",
  "geometry": {
    "type": "Point",
    "coordinates": [
      -148.658,
      61.3192
    ]
  },
  "properties": {
    "name": "Mt. Palmer",
    "latitude": 61.3192,
    "longitude": -148.658,
    "feet": 6970,
    "meters": 2,
    "continent": "North America",
    "country": "United States",
    "state": "Alaska"
  }
}
