{
  "type": "Feature",
  "geometry": {
    "type": "Point",
    "coordinates": [
      -149.533,
      60.1167
    ]
  },
  "properties": {
    "name": "Phoenix Peak",
    "latitude": 60.1167,
    "longitude": -149.533,
    "feet": 5155,
    "meters": 1571,
    "continent": "North America",
    "country": "United States",
    "state": "Alaska"
  }
}
