{
  "type": "Feature",
  "geometry": {
    "type": "Point",
    "coordinates": [
      11.1167,
      47.4167
    ]
  },
  "properties": {
    "name": "Hochwand",
    "latitude": 47.4167,
    "longitude": 11.1167,
    "feet": 8934,
    "meters": 2723,
    "continent": "Europe",
    "country": "Austria"
  }
}
