{
  "type": "Feature",
  "geometry": {
    "type": "Point",
    "coordinates": [
      11.0833,
      47.3333
    ]
  },
  "properties": {
    "name": "Hohe Munde",
    "latitude": 47.3333,
    "longitude": 11.0833,
    "feet": 8733,
    "meters": 2662,
    "continent": "Europe",
    "country": "Austria"
  }
}
