{
  "type": "Feature",
  "geometry": {
    "type": "Point",
    "coordinates": [
      13.569317,
      47.754444
    ]
  },
  "properties": {
    "name": "Leonsberg",
    "latitude": 47.754444,
    "longitude": 13.569317,
    "feet": 5584,
    "meters": 1702,
    "continent": "Europe",
    "country": "Austria"
  }
}
