{
  "type": "Feature",
  "geometry": {
    "type": "Point",
    "coordinates": [
      2.116585,
      42.383148
    ]
  },
  "properties": {
    "name": "Puigmal",
    "latitude": 42.383148,
    "longitude": 2.116585,
    "feet": 9537,
    "meters": 2907,
    "continent": "Europe",
    "country": "Spain/France"
  }
}
