{
  "type": "Feature",
  "geometry": {
    "type": "Point",
    "coordinates": [
      -79.1761,
      39.7861
    ]
  },
  "properties": {
    "name": "Mount Davis",
    "latitude": 39.7861,
    "longitude": -79.1761,
    "feet": 3213,
    "meters": 979,
    "continent": "North America",
    "country": "United States",
    "state": "Pennsylvania"
  }
}
