{
  "type": "Feature",
  "geometry": {
    "type": "Point",
    "coordinates": [
      114.872,
      4.04647
    ]
  },
  "properties": {
    "name": "Bukit Batu Bujang Pahang",
    "latitude": 4.04647,
    "longitude": 114.872,
    "feet": 230,
    "meters": 70,
    "continent": "Asia",
    "country": "Brunei",
    "marker-symbol": "triangle",
    "marker-size": "small"
  }
}
