{
  "type": "Feature",
  "geometry": {
    "type": "Point",
    "coordinates": [
      -100.234,
      25.6327
    ]
  },
  "properties": {
    "name": "Cerro De La Silla",
    "latitude": 25.6327,
    "longitude": -100.234,
    "feet": 5971,
    "meters": 1820,
    "continent": "North America",
    "country": "Mexico"
  }
}
