{
  "type": "Feature",
  "geometry": {
    "type": "Point",
    "coordinates": [
      -106.143,
      39.6167
    ]
  },
  "properties": {
    "name": "Buffalo Mountain",
    "latitude": 39.6167,
    "longitude": -106.143,
    "feet": 12777,
    "meters": 3894,
    "continent": "North America",
    "country": "United States",
    "marker-symbol": "triangle",
    "marker-size": "small"
  }
}
