{
  "type": "Feature",
  "geometry": {
    "type": "Point",
    "coordinates": [
      9.571389,
      47.175
    ]
  },
  "properties": {
    "name": "Drei Schwestern",
    "latitude": 47.175,
    "longitude": 9.571389,
    "feet": 6736,
    "meters": 2053,
    "continent": "Europe",
    "country": "Liechtenstein"
  }
}
