{
  "type": "Feature",
  "geometry": {
    "type": "Point",
    "coordinates": [
      -111.65,
      41.95
    ]
  },
  "properties": {
    "name": "Doubletop Mountain",
    "latitude": 41.95,
    "longitude": -111.65,
    "feet": 9873,
    "meters": 3009,
    "continent": "North America",
    "country": "United States",
    "state": "Utah"
  }
}
