{
  "type": "Feature",
  "geometry": {
    "type": "Point",
    "coordinates": [
      -110.367,
      40.7833
    ]
  },
  "properties": {
    "name": "Kings Peak",
    "latitude": 40.7833,
    "longitude": -110.367,
    "feet": 13528,
    "meters": 4123,
    "continent": "North America",
    "country": "United States",
    "state": "Utah"
  }
}
