{
  "type": "Feature",
  "geometry": {
    "type": "Point",
    "coordinates": [
      -6.321879,
      42.801438
    ]
  },
  "properties": {
    "name": "Catoute",
    "latitude": 42.801438,
    "longitude": -6.321879,
    "feet": 6946,
    "meters": 2117,
    "continent": "Europe",
    "country": "Spain",
    "marker-symbol": "triangle",
    "marker-size": "small"
  }
}
