{
  "type": "Feature",
  "geometry": {
    "type": "Point",
    "coordinates": [
      -4.79402,
      43.0861
    ]
  },
  "properties": {
    "name": "Coriscao",
    "latitude": 43.0861,
    "longitude": -4.79402,
    "feet": 7329,
    "meters": 2234,
    "continent": "Europe",
    "country": "Spain"
  }
}
