{
  "type": "Feature",
  "geometry": {
    "type": "Point",
    "coordinates": [
      -0.7264,
      42.3507
    ]
  },
  "properties": {
    "name": "Mallos de Riglos",
    "latitude": 42.3507,
    "longitude": -0.7264,
    "feet": 3428,
    "meters": 1045,
    "continent": "Europe",
    "country": "Spain"
  }
}
