{
  "type": "Feature",
  "geometry": {
    "type": "Point",
    "coordinates": [
      2.180185,
      42.418451
    ]
  },
  "properties": {
    "name": "Torreneules",
    "latitude": 42.418451,
    "longitude": 2.180185,
    "feet": 8894,
    "meters": 2711,
    "continent": "Europe",
    "country": "Spain",
    "marker-symbol": "triangle",
    "marker-size": "small"
  }
}
