{
  "type": "Feature",
  "geometry": {
    "type": "Point",
    "coordinates": [
      -78.437778,
      -0.680556
    ]
  },
  "properties": {
    "name": "Cotopaxi",
    "latitude": -0.680556,
    "longitude": -78.437778,
    "feet": 19347,
    "meters": 5897,
    "continent": "South America",
    "country": "Ecuador"
  }
}
