{
  "type": "Feature",
  "geometry": {
    "type": "Point",
    "coordinates": [
      -66.272665,
      -17.239812
    ]
  },
  "properties": {
    "name": "Cerro Santiago",
    "latitude": -17.239812,
    "longitude": -66.272665,
    "feet": 14974,
    "meters": 4564,
    "continent": "South America",
    "country": "Bolivia",
    "marker-symbol": "triangle",
    "marker-size": "small"
  }
}
