{
  "type": "Feature",
  "geometry": {
    "type": "Point",
    "coordinates": [
      -3.74445,
      52.917908
    ]
  },
  "properties": {
    "name": "Arenig Fawr",
    "latitude": 52.917908,
    "longitude": -3.74445,
    "feet": 2801,
    "meters": 854,
    "continent": "Europe",
    "country": "United Kingdom/United Kingdom"
  }
}
