{
  "type": "Feature",
  "geometry": {
    "type": "Point",
    "coordinates": [
      -3.25,
      56.9186
    ]
  },
  "properties": {
    "name": "Broad Cairn",
    "latitude": 56.9186,
    "longitude": -3.25,
    "feet": 3274,
    "meters": 998,
    "continent": "Europe",
    "country": "United Kingdom/United Kingdom",
    "marker-symbol": "triangle",
    "marker-size": "small"
  }
}
