{
  "type": "Feature",
  "geometry": {
    "type": "Point",
    "coordinates": [
      16.507623,
      44.432087
    ]
  },
  "properties": {
    "name": "Velika Klekovača",
    "latitude": 44.432087,
    "longitude": 16.507623,
    "feet": 6444,
    "meters": 1964,
    "continent": "Europe",
    "country": "Bosnia and Herzegovina/Bosnia and Herzegovina",
    "marker-symbol": "triangle",
    "marker-size": "small"
  }
}
