{
  "type": "Feature",
  "geometry": {
    "type": "Point",
    "coordinates": [
      -83.4933,
      35.5417
    ]
  },
  "properties": {
    "name": "Andrews Bald",
    "latitude": 35.5417,
    "longitude": -83.4933,
    "feet": 5860,
    "meters": 1786,
    "continent": "North America",
    "country": "United States",
    "state": "North Carolina"
  }
}
