{
  "type": "Feature",
  "geometry": {
    "type": "Point",
    "coordinates": [
      -81.8944,
      35.8383
    ]
  },
  "properties": {
    "name": "Shortoff Mountain",
    "latitude": 35.8383,
    "longitude": -81.8944,
    "feet": 2920,
    "meters": 890,
    "continent": "North America",
    "country": "United States",
    "state": "North Carolina",
    "marker-symbol": "triangle",
    "marker-size": "small"
  }
}
