{
  "type": "Feature",
  "geometry": {
    "type": "Point",
    "coordinates": [
      35.648,
      76.6697
    ]
  },
  "properties": {
    "name": "Baltoro Kangri",
    "latitude": 76.6697,
    "longitude": 35.648,
    "feet": 23835,
    "meters": 7265,
    "continent": "Asia",
    "country": "Pakistan"
  }
}
