{
  "type": "Feature",
  "geometry": {
    "type": "Point",
    "coordinates": [
      76.5667,
      35.8167
    ]
  },
  "properties": {
    "name": "Broad Peak",
    "latitude": 35.8167,
    "longitude": 76.5667,
    "feet": 26400,
    "meters": 8047,
    "continent": "Asia",
    "country": "Pakistan",
    "marker-symbol": "triangle",
    "marker-size": "small"
  }
}
