{
  "type": "Feature",
  "geometry": {
    "type": "Point",
    "coordinates": [
      -83.509942,
      9.475472
    ]
  },
  "properties": {
    "name": "Cerro Vantisqueros",
    "latitude": 9.475472,
    "longitude": -83.509942,
    "feet": 12507,
    "meters": 3812,
    "continent": "North America",
    "country": "Costa Rica",
    "marker-symbol": "triangle",
    "marker-size": "small"
  }
}
