{
  "type": "Feature",
  "geometry": {
    "type": "Point",
    "coordinates": [
      138.517,
      36.4057
    ]
  },
  "properties": {
    "name": "Asama Yama",
    "latitude": 36.4057,
    "longitude": 138.517,
    "feet": 8425,
    "meters": 2568,
    "continent": "Asia",
    "country": "Japan",
    "marker-symbol": "triangle",
    "marker-size": "small"
  }
}
