{
  "type": "Feature",
  "geometry": {
    "type": "Point",
    "coordinates": [
      -117.5089,
      45.1561
    ]
  },
  "properties": {
    "name": "China Cap",
    "latitude": 45.1561,
    "longitude": -117.5089,
    "feet": 8656,
    "meters": 2638,
    "continent": "North America",
    "country": "United States",
    "state": "Oregon",
    "marker-symbol": "triangle",
    "marker-size": "small"
  }
}
