{
  "type": "Feature",
  "geometry": {
    "type": "Point",
    "coordinates": [
      -122.053898,
      43.399881
    ]
  },
  "properties": {
    "name": "Cowhorn Mountain",
    "latitude": 43.399881,
    "longitude": -122.053898,
    "feet": 7664,
    "meters": 2336,
    "continent": "North America",
    "country": "United States",
    "state": "Oregon"
  }
}
