{
  "type": "Feature",
  "geometry": {
    "type": "Point",
    "coordinates": [
      -122.616606,
      42.269592
    ]
  },
  "properties": {
    "name": "Grizzly Peak",
    "latitude": 42.269592,
    "longitude": -122.616606,
    "feet": 5920,
    "meters": 1804,
    "continent": "North America",
    "country": "United States",
    "state": "Oregon"
  }
}
