{
  "type": "Feature",
  "geometry": {
    "type": "Point",
    "coordinates": [
      -122.219982,
      43.155105
    ]
  },
  "properties": {
    "name": "Mount Bailey",
    "latitude": 43.155105,
    "longitude": -122.219982,
    "feet": 8368,
    "meters": 2551,
    "continent": "North America",
    "country": "United States",
    "state": "Oregon",
    "marker-symbol": "triangle",
    "marker-size": "small"
  }
}
