{
  "type": "Feature",
  "geometry": {
    "type": "Point",
    "coordinates": [
      -121.283259,
      44.060521
    ]
  },
  "properties": {
    "name": "Pilot Butte",
    "latitude": 44.060521,
    "longitude": -121.283259,
    "feet": 4142,
    "meters": 1262,
    "continent": "North America",
    "country": "United States",
    "state": "Oregon"
  }
}
