{
  "type": "Feature",
  "geometry": {
    "type": "Point",
    "coordinates": [
      -121.8431,
      44.479054
    ]
  },
  "properties": {
    "name": "Three Fingered Jack",
    "latitude": 44.479054,
    "longitude": -121.8431,
    "feet": 7841,
    "meters": 2390,
    "continent": "North America",
    "country": "United States",
    "state": "Oregon",
    "marker-symbol": "triangle",
    "marker-size": "small"
  }
}
