{
  "type": "Feature",
  "geometry": {
    "type": "Point",
    "coordinates": [
      -120.873771,
      47.508331
    ]
  },
  "properties": {
    "name": "Axis Mountain",
    "latitude": 47.508331,
    "longitude": -120.873771,
    "feet": 7550,
    "meters": 2301,
    "continent": "North America",
    "country": "United States",
    "state": "Washington"
  }
}
