{
  "type": "Feature",
  "geometry": {
    "type": "Point",
    "coordinates": [
      -121.225,
      47.5401
    ]
  },
  "properties": {
    "name": "Bears Breast Mountain",
    "latitude": 47.5401,
    "longitude": -121.225,
    "feet": 7197,
    "meters": 2194,
    "continent": "North America",
    "country": "United States",
    "state": "Washington"
  }
}
