{
  "type": "Feature",
  "geometry": {
    "type": "Point",
    "coordinates": [
      -121.361332,
      47.961537
    ]
  },
  "properties": {
    "name": "Columbia Peak",
    "latitude": 47.961537,
    "longitude": -121.361332,
    "feet": 7172,
    "meters": 2186,
    "continent": "North America",
    "country": "United States",
    "state": "Washington"
  }
}
