{
  "type": "Feature",
  "geometry": {
    "type": "Point",
    "coordinates": [
      -120.598297,
      48.442241
    ]
  },
  "properties": {
    "name": "Crescent Mountain",
    "latitude": 48.442241,
    "longitude": -120.598297,
    "feet": 7816,
    "meters": 2382,
    "continent": "North America",
    "country": "United States",
    "state": "Washington"
  }
}
