{
  "type": "Feature",
  "geometry": {
    "type": "Point",
    "coordinates": [
      -120.721979,
      48.559
    ]
  },
  "properties": {
    "name": "Cumulus Mtn.",
    "latitude": 48.559,
    "longitude": -120.721979,
    "feet": 7340,
    "meters": 2237,
    "continent": "North America",
    "country": "United States",
    "state": "Washington"
  }
}
