{
  "type": "Feature",
  "geometry": {
    "type": "Point",
    "coordinates": [
      -121.202888,
      48.729389
    ]
  },
  "properties": {
    "name": "Davis Peak",
    "latitude": 48.729389,
    "longitude": -121.202888,
    "feet": 7051,
    "meters": 2149,
    "continent": "North America",
    "country": "United States",
    "state": "Washington"
  }
}
