{
  "type": "Feature",
  "geometry": {
    "type": "Point",
    "coordinates": [
      -120.708246,
      48.562494
    ]
  },
  "properties": {
    "name": "Gentle Mountain",
    "latitude": 48.562494,
    "longitude": -120.708246,
    "feet": 7552,
    "meters": 2302,
    "continent": "North America",
    "country": "United States",
    "state": "Washington"
  }
}
