{
  "type": "Feature",
  "geometry": {
    "type": "Point",
    "coordinates": [
      -121.384807,
      47.443037
    ]
  },
  "properties": {
    "name": "Kendall Peak",
    "latitude": 47.443037,
    "longitude": -121.384807,
    "feet": 5784,
    "meters": 1763,
    "continent": "North America",
    "country": "United States",
    "state": "Washington"
  }
}
