{
  "type": "Feature",
  "geometry": {
    "type": "Point",
    "coordinates": [
      -120.657,
      48.5142
    ]
  },
  "properties": {
    "name": "Lexington Tower",
    "latitude": 48.5142,
    "longitude": -120.657,
    "feet": 7560,
    "meters": 2304,
    "continent": "North America",
    "country": "United States",
    "state": "Washington"
  }
}
