{
  "type": "Feature",
  "geometry": {
    "type": "Point",
    "coordinates": [
      -121.300864,
      48.95782
    ]
  },
  "properties": {
    "name": "Mount Redoubt",
    "latitude": 48.95782,
    "longitude": -121.300864,
    "feet": 8969,
    "meters": 2734,
    "continent": "North America",
    "country": "United States",
    "state": "Washington"
  }
}
