{
  "type": "Feature",
  "geometry": {
    "type": "Point",
    "coordinates": [
      -121.762247,
      48.31494
    ]
  },
  "properties": {
    "name": "Mount Higgins East",
    "latitude": 48.31494,
    "longitude": -121.762247,
    "feet": 5142,
    "meters": 1567,
    "continent": "North America",
    "country": "United States",
    "state": "Washington"
  }
}
