{
  "type": "Feature",
  "geometry": {
    "type": "Point",
    "coordinates": [
      -121.750832,
      48.326468
    ]
  },
  "properties": {
    "name": "Round Mountain",
    "latitude": 48.326468,
    "longitude": -121.750832,
    "feet": 5320,
    "meters": 1622,
    "continent": "North America",
    "country": "United States",
    "state": "Washington"
  }
}
