{
  "type": "Feature",
  "geometry": {
    "type": "Point",
    "coordinates": [
      -121.042943,
      48.694388
    ]
  },
  "properties": {
    "name": "Ruby Mountain",
    "latitude": 48.694388,
    "longitude": -121.042943,
    "feet": 7408,
    "meters": 2258,
    "continent": "North America",
    "country": "United States",
    "state": "Washington"
  }
}
