{
  "type": "Feature",
  "geometry": {
    "type": "Point",
    "coordinates": [
      -121.530547,
      46.813571
    ]
  },
  "properties": {
    "name": "Shriner Peak",
    "latitude": 46.813571,
    "longitude": -121.530547,
    "feet": 5834,
    "meters": 1768,
    "continent": "North America",
    "country": "United States",
    "state": "Washington",
    "marker-symbol": "triangle",
    "marker-size": "small"
  }
}
