{
  "type": "Feature",
  "geometry": {
    "type": "Point",
    "coordinates": [
      -121.737828,
      46.945868
    ]
  },
  "properties": {
    "name": "Sluiskin Mountain",
    "latitude": 46.945868,
    "longitude": -121.737828,
    "feet": 7026,
    "meters": 2142,
    "continent": "North America",
    "country": "United States",
    "state": "Washington",
    "marker-symbol": "triangle",
    "marker-size": "small"
  }
}
