{
  "type": "Feature",
  "geometry": {
    "type": "Point",
    "coordinates": [
      -120.704169,
      48.588474
    ]
  },
  "properties": {
    "name": "Tower Mountain",
    "latitude": 48.588474,
    "longitude": -120.704169,
    "feet": 8444,
    "meters": 2574,
    "continent": "North America",
    "country": "United States",
    "state": "Washington",
    "marker-symbol": "triangle",
    "marker-size": "small"
  }
}
