{
  "type": "Feature",
  "geometry": {
    "type": "Point",
    "coordinates": [
      -121.01788,
      48.431735
    ]
  },
  "properties": {
    "name": "Trapper Mountain",
    "latitude": 48.431735,
    "longitude": -121.01788,
    "feet": 7530,
    "meters": 2295,
    "continent": "North America",
    "country": "United States",
    "state": "Washington",
    "marker-symbol": "triangle",
    "marker-size": "small"
  }
}
