{
  "type": "Feature",
  "geometry": {
    "type": "Point",
    "coordinates": [
      7.564168,
      45.689439
    ]
  },
  "properties": {
    "name": "Avic",
    "latitude": 45.689439,
    "longitude": 7.564168,
    "feet": 9862,
    "meters": 3006,
    "continent": "Europe",
    "country": "Italy"
  }
}
