{
  "type": "Feature",
  "geometry": {
    "type": "Point",
    "coordinates": [
      10.898473,
      46.184616
    ]
  },
  "properties": {
    "name": "Brenta Alta",
    "latitude": 46.184616,
    "longitude": 10.898473,
    "feet": 9711,
    "meters": 2960,
    "continent": "Europe",
    "country": "Italy",
    "marker-symbol": "triangle",
    "marker-size": "small"
  }
}
