{
  "type": "Feature",
  "geometry": {
    "type": "Point",
    "coordinates": [
      10.8946,
      46.1615
    ]
  },
  "properties": {
    "name": "Campanile Basso",
    "latitude": 46.1615,
    "longitude": 10.8946,
    "feet": 9439,
    "meters": 2877,
    "continent": "Europe",
    "country": "Italy"
  }
}
