{
  "type": "Feature",
  "geometry": {
    "type": "Point",
    "coordinates": [
      11.960893,
      46.622385
    ]
  },
  "properties": {
    "name": "Croda di Santa Croce",
    "latitude": 46.622385,
    "longitude": 11.960893,
    "feet": 9928,
    "meters": 3026,
    "continent": "Europe",
    "country": "Italy"
  }
}
