{
  "type": "Feature",
  "geometry": {
    "type": "Point",
    "coordinates": [
      13.491461,
      46.430168
    ]
  },
  "properties": {
    "name": "Jof Fuart",
    "latitude": 46.430168,
    "longitude": 13.491461,
    "feet": 8747,
    "meters": 2666,
    "continent": "Europe",
    "country": "Italy"
  }
}
