{
  "type": "Feature",
  "geometry": {
    "type": "Point",
    "coordinates": [
      11.8478,
      46.2541
    ]
  },
  "properties": {
    "name": "Pala di San Martino",
    "latitude": 46.2541,
    "longitude": 11.8478,
    "feet": 9800,
    "meters": 2987,
    "continent": "Europe",
    "country": "Italy"
  }
}
