{
  "type": "Feature",
  "geometry": {
    "type": "Point",
    "coordinates": [
      7.339335,
      45.658282
    ]
  },
  "properties": {
    "name": "Punta della Valletta",
    "latitude": 45.658282,
    "longitude": 7.339335,
    "feet": 10138,
    "meters": 3090,
    "continent": "Europe",
    "country": "Italy"
  }
}
