{
  "type": "Feature",
  "geometry": {
    "type": "Point",
    "coordinates": [
      14.4333,
      40.8167
    ]
  },
  "properties": {
    "name": "Vesuvius",
    "latitude": 40.8167,
    "longitude": 14.4333,
    "feet": 4202,
    "meters": 1281,
    "continent": "Europe",
    "country": "Italy",
    "marker-symbol": "triangle",
    "marker-size": "small"
  }
}
