{
  "type": "Feature",
  "geometry": {
    "type": "Point",
    "coordinates": [
      123.221768,
      10.782744
    ]
  },
  "properties": {
    "name": "Dinamlagan Peak",
    "latitude": 10.782744,
    "longitude": 123.221768,
    "feet": 4839,
    "meters": 1475,
    "continent": "Asia",
    "country": "Philippines"
  }
}
