{
  "type": "Feature",
  "geometry": {
    "type": "Point",
    "coordinates": [
      122.706349,
      11.042576
    ]
  },
  "properties": {
    "name": "Hamugnaw Peak",
    "latitude": 11.042576,
    "longitude": 122.706349,
    "feet": 755,
    "meters": 230,
    "continent": "Asia",
    "country": "Philippines"
  }
}
