{
  "type": "Feature",
  "geometry": {
    "type": "Point",
    "coordinates": [
      122.370665,
      11.103097
    ]
  },
  "properties": {
    "name": "Mount Agdalusan",
    "latitude": 11.103097,
    "longitude": 122.370665,
    "feet": 2526,
    "meters": 770,
    "continent": "Asia",
    "country": "Philippines"
  }
}
