{
  "type": "Feature",
  "geometry": {
    "type": "Point",
    "coordinates": [
      123.383,
      13.6667
    ]
  },
  "properties": {
    "name": "Mt. Isarog",
    "latitude": 13.6667,
    "longitude": 123.383,
    "feet": 6450,
    "meters": 1966,
    "continent": "Asia",
    "country": "Philippines"
  }
}
