{
  "type": "Feature",
  "geometry": {
    "type": "Point",
    "coordinates": [
      120.801,
      16.318
    ]
  },
  "properties": {
    "name": "Mt. Ugo",
    "latitude": 16.318,
    "longitude": 120.801,
    "feet": 7054,
    "meters": 2150,
    "continent": "Asia",
    "country": "Philippines",
    "marker-symbol": "triangle",
    "marker-size": "small"
  }
}
