{
  "type": "Feature",
  "geometry": {
    "type": "Point",
    "coordinates": [
      -73.0333,
      -49.2833
    ]
  },
  "properties": {
    "name": "Aguja Saint Exupery",
    "latitude": -49.2833,
    "longitude": -73.0333,
    "feet": 2680,
    "meters": 817,
    "continent": "South America",
    "country": "Argentina"
  }
}
