{
  "type": "Feature",
  "geometry": {
    "type": "Point",
    "coordinates": [
      -69.3833,
      -32.9667
    ]
  },
  "properties": {
    "name": "Cerro San Bernardo",
    "latitude": -32.9667,
    "longitude": -69.3833,
    "feet": 13451,
    "meters": 4100,
    "continent": "South America",
    "country": "Argentina"
  }
}
