{
  "type": "Feature",
  "geometry": {
    "type": "Point",
    "coordinates": [
      -69.4167,
      -33.0167
    ]
  },
  "properties": {
    "name": "Plata",
    "latitude": -33.0167,
    "longitude": -69.4167,
    "feet": 20718,
    "meters": 6315,
    "continent": "South America",
    "country": "Argentina"
  }
}
