{
  "type": "Feature",
  "geometry": {
    "type": "Point",
    "coordinates": [
      -119.333,
      37.0167
    ]
  },
  "properties": {
    "name": "Little Baldy",
    "latitude": 37.0167,
    "longitude": -119.333,
    "feet": 8044,
    "meters": 2452,
    "continent": "North America",
    "country": "United States",
    "state": "California"
  }
}
