{
  "type": "Feature",
  "geometry": {
    "type": "Point",
    "coordinates": [
      -118.658,
      37.3386
    ]
  },
  "properties": {
    "name": "Mount Tom",
    "latitude": 37.3386,
    "longitude": -118.658,
    "feet": 13652,
    "meters": 4161,
    "continent": "North America",
    "country": "United States",
    "state": "California",
    "marker-symbol": "triangle",
    "marker-size": "small"
  }
}
