{
  "type": "Feature",
  "geometry": {
    "type": "Point",
    "coordinates": [
      -117.76464,
      34.35853
    ]
  },
  "properties": {
    "name": "Mount Baden-Powell",
    "latitude": 34.35853,
    "longitude": -117.76464,
    "feet": 9399,
    "meters": 2865,
    "continent": "North America",
    "country": "United States",
    "state": "California"
  }
}
