{
  "type": "Feature",
  "geometry": {
    "type": "Point",
    "coordinates": [
      -118.671,
      37.1669
    ]
  },
  "properties": {
    "name": "Mount Darwin",
    "latitude": 37.1669,
    "longitude": -118.671,
    "feet": 13831,
    "meters": 4216,
    "continent": "North America",
    "country": "United States",
    "state": "California"
  }
}
