{
  "type": "Feature",
  "geometry": {
    "type": "Point",
    "coordinates": [
      -118.661,
      37.1503
    ]
  },
  "properties": {
    "name": "Mount Haeckel",
    "latitude": 37.1503,
    "longitude": -118.661,
    "feet": 13435,
    "meters": 4095,
    "continent": "North America",
    "country": "United States",
    "state": "California"
  }
}
