{
  "type": "Feature",
  "geometry": {
    "type": "Point",
    "coordinates": [
      -119.314,
      37.9822
    ]
  },
  "properties": {
    "name": "North Peak",
    "latitude": 37.9822,
    "longitude": -119.314,
    "feet": 12242,
    "meters": 3731,
    "continent": "North America",
    "country": "United States",
    "state": "California"
  }
}
