{
  "type": "Feature",
  "geometry": {
    "type": "Point",
    "coordinates": [
      -116.828,
      34.1006
    ]
  },
  "properties": {
    "name": "San Gorgonio",
    "latitude": 34.1006,
    "longitude": -116.828,
    "feet": 11499,
    "meters": 3505,
    "continent": "North America",
    "country": "United States",
    "state": "California"
  }
}
