{
  "type": "Feature",
  "geometry": {
    "type": "Point",
    "coordinates": [
      145.029316,
      -5.779966
    ]
  },
  "properties": {
    "name": "Mount Wilhelm",
    "latitude": -5.779966,
    "longitude": 145.029316,
    "feet": 14793,
    "meters": 4509,
    "continent": "Australia/Oceania",
    "country": "Papua New Guinea",
    "marker-symbol": "triangle",
    "marker-size": "small"
  }
}
