{
  "type": "Feature",
  "geometry": {
    "type": "Point",
    "coordinates": [
      -71.0011,
      8.54583
    ]
  },
  "properties": {
    "name": "Bonpland",
    "latitude": 8.54583,
    "longitude": -71.0011,
    "feet": 16043,
    "meters": 4890,
    "continent": "South America",
    "country": "Venezuela"
  }
}
