{
  "type": "Feature",
  "geometry": {
    "type": "Point",
    "coordinates": [
      -63.9114,
      10.9958
    ]
  },
  "properties": {
    "name": "Cerro Copey",
    "latitude": 10.9958,
    "longitude": -63.9114,
    "feet": 3150,
    "meters": 960,
    "continent": "South America",
    "country": "Venezuela"
  }
}
