{
  "type": "Feature",
  "geometry": {
    "type": "Point",
    "coordinates": [
      -63.958411,
      10.08384
    ]
  },
  "properties": {
    "name": "Cerro Tristeza",
    "latitude": 10.08384,
    "longitude": -63.958411,
    "feet": 8514,
    "meters": 2595,
    "continent": "South America",
    "country": "Venezuela"
  }
}
