{
  "type": "Feature",
  "geometry": {
    "type": "Point",
    "coordinates": [
      -68.80012,
      10.404248
    ]
  },
  "properties": {
    "name": "Cerro Tigre",
    "latitude": 10.404248,
    "longitude": -68.80012,
    "feet": 6381,
    "meters": 1945,
    "continent": "South America",
    "country": "Venezuela",
    "marker-symbol": "triangle",
    "marker-size": "small"
  }
}
