{
  "type": "Feature",
  "geometry": {
    "type": "Point",
    "coordinates": [
      -66.394672,
      9.974472
    ]
  },
  "properties": {
    "name": "Cerro Santa Inés",
    "latitude": 9.974472,
    "longitude": -66.394672,
    "feet": 4134,
    "meters": 1260,
    "continent": "South America",
    "country": "Venezuela",
    "marker-symbol": "triangle",
    "marker-size": "small"
  }
}
