{
  "type": "Feature",
  "geometry": {
    "type": "Point",
    "coordinates": [
      -69.951453,
      11.818419
    ]
  },
  "properties": {
    "name": "Cerro Santa Ana",
    "latitude": 11.818419,
    "longitude": -69.951453,
    "feet": 2625,
    "meters": 830,
    "continent": "South America",
    "country": "Venezuela",
    "marker-symbol": "triangle",
    "marker-size": "small"
  }
}
