{
  "type": "Feature",
  "geometry": {
    "type": "Point",
    "coordinates": [
      -70.693588,
      8.780582
    ]
  },
  "properties": {
    "name": "Granate",
    "latitude": 8.780582,
    "longitude": -70.693588,
    "feet": 12765,
    "meters": 3891,
    "continent": "South America",
    "country": "Venezuela"
  }
}
