{
  "type": "Feature",
  "geometry": {
    "type": "Point",
    "coordinates": [
      -134.291069,
      58.707971
    ]
  },
  "properties": {
    "name": "Taku D Peak",
    "latitude": 58.707971,
    "longitude": -134.291069,
    "feet": 5810,
    "meters": 1771,
    "continent": "North America",
    "country": "United States/United States",
    "state": "Alaska/Alaska",
    "marker-symbol": "triangle",
    "marker-size": "small"
  }
}
