{
  "type": "Feature",
  "geometry": {
    "type": "Point",
    "coordinates": [
      152.614396,
      -28.269393
    ]
  },
  "properties": {
    "name": "Mt Ballow",
    "latitude": -28.269393,
    "longitude": 152.614396,
    "feet": 4308,
    "meters": 1313,
    "continent": "Australia/Oceania",
    "country": "Australia"
  }
}
