{
  "type": "Feature",
  "geometry": {
    "type": "Point",
    "coordinates": [
      -9.711914,
      53.761702
    ]
  },
  "properties": {
    "name": "Croagh Patrick",
    "latitude": 53.761702,
    "longitude": -9.711914,
    "feet": 2493,
    "meters": 760,
    "continent": "Europe",
    "country": "Ireland"
  }
}
