{
  "type": "Feature",
  "geometry": {
    "type": "Point",
    "coordinates": [
      51.588192,
      36.108201
    ]
  },
  "properties": {
    "name": "Khole-no",
    "latitude": 36.108201,
    "longitude": 51.588192,
    "feet": 14354,
    "meters": 4375,
    "continent": "Asia",
    "country": "Iran"
  }
}
