{
  "type": "Feature",
  "geometry": {
    "type": "Point",
    "coordinates": [
      -8.158422,
      41.766991
    ]
  },
  "properties": {
    "name": "Pé de Cabril",
    "latitude": 41.766991,
    "longitude": -8.158422,
    "feet": 4058,
    "meters": 1237,
    "continent": "Europe",
    "country": "Portugal"
  }
}
