{
  "type": "Feature",
  "geometry": {
    "type": "Point",
    "coordinates": [
      116.467,
      -8.43333
    ]
  },
  "properties": {
    "name": "Gunung Rinjani",
    "latitude": -8.43333,
    "longitude": 116.467,
    "feet": 12224,
    "meters": 3726,
    "continent": "Asia",
    "country": "Indonesia"
  }
}
