{
  "type": "Feature",
  "geometry": {
    "type": "Point",
    "coordinates": [
      -111.595,
      31.7711
    ]
  },
  "properties": {
    "name": "Baboquivari Peak",
    "latitude": 31.7711,
    "longitude": -111.595,
    "feet": 7730,
    "meters": 2356,
    "continent": "North America",
    "country": "United States",
    "state": "Arizona"
  }
}
