{
  "type": "Feature",
  "geometry": {
    "type": "Point",
    "coordinates": [
      -110.75,
      31.3333
    ]
  },
  "properties": {
    "name": "Mount Washington",
    "latitude": 31.3333,
    "longitude": -110.75,
    "feet": 7221,
    "meters": 2201,
    "continent": "North America",
    "country": "United States",
    "state": "Arizona",
    "marker-symbol": "triangle",
    "marker-size": "small"
  }
}
