{
  "type": "Feature",
  "geometry": {
    "type": "Point",
    "coordinates": [
      -110.715,
      32.4155
    ]
  },
  "properties": {
    "name": "Mount Bigelow",
    "latitude": 32.4155,
    "longitude": -110.715,
    "feet": 8550,
    "meters": 2606,
    "continent": "North America",
    "country": "United States",
    "state": "Arizona"
  }
}
