{
  "type": "Feature",
  "geometry": {
    "type": "Point",
    "coordinates": [
      -4.81763,
      56.2376
    ]
  },
  "properties": {
    "name": "Beinn Ime",
    "latitude": 56.2376,
    "longitude": -4.81763,
    "feet": 3317,
    "meters": 1011,
    "continent": "Europe",
    "country": "United Kingdom"
  }
}
