{
  "type": "Feature",
  "geometry": {
    "type": "Point",
    "coordinates": [
      -6.09312,
      57.2196
    ]
  },
  "properties": {
    "name": "Bla Bheinn",
    "latitude": 57.2196,
    "longitude": -6.09312,
    "feet": 3044,
    "meters": 928,
    "continent": "Europe",
    "country": "United Kingdom"
  }
}
