{
  "type": "Feature",
  "geometry": {
    "type": "Point",
    "coordinates": [
      -3.04978,
      54.64
    ]
  },
  "properties": {
    "name": "Blencathra",
    "latitude": 54.64,
    "longitude": -3.04978,
    "feet": 2847,
    "meters": 868,
    "continent": "Europe",
    "country": "United Kingdom"
  }
}
