{
  "type": "Feature",
  "geometry": {
    "type": "Point",
    "coordinates": [
      -4.986763,
      56.805272
    ]
  },
  "properties": {
    "name": "Carn Mor Dearg",
    "latitude": 56.805272,
    "longitude": -4.986763,
    "feet": 4002,
    "meters": 1220,
    "continent": "Europe",
    "country": "United Kingdom",
    "marker-symbol": "triangle",
    "marker-size": "small"
  }
}
