{
  "type": "Feature",
  "geometry": {
    "type": "Point",
    "coordinates": [
      -3.437133,
      51.884333
    ]
  },
  "properties": {
    "name": "Corn Du",
    "latitude": 51.884333,
    "longitude": -3.437133,
    "feet": 2864,
    "meters": 873,
    "continent": "Europe",
    "country": "United Kingdom"
  }
}
