{
  "type": "Feature",
  "geometry": {
    "type": "Point",
    "coordinates": [
      -4.003315,
      53.105877
    ]
  },
  "properties": {
    "name": "Glyder Fach",
    "latitude": 53.105877,
    "longitude": -4.003315,
    "feet": 3248,
    "meters": 990,
    "continent": "Europe",
    "country": "United Kingdom"
  }
}
