{
  "type": "Feature",
  "geometry": {
    "type": "Point",
    "coordinates": [
      -104.667,
      31.8333
    ]
  },
  "properties": {
    "name": "El Capitan",
    "latitude": 31.8333,
    "longitude": -104.667,
    "feet": 8085,
    "meters": 2464,
    "continent": "North America",
    "country": "United States",
    "state": "Texas"
  }
}
