{
  "type": "Feature",
  "geometry": {
    "type": "Point",
    "coordinates": [
      -104.867,
      31.8833
    ]
  },
  "properties": {
    "name": "Guadalupe Peak",
    "latitude": 31.8833,
    "longitude": -104.867,
    "feet": 8749,
    "meters": 2667,
    "continent": "North America",
    "country": "United States",
    "state": "Texas"
  }
}
