{
  "type": "Feature",
  "geometry": {
    "type": "Point",
    "coordinates": [
      -113.68924,
      48.71024
    ]
  },
  "properties": {
    "name": "Piegan Mountain",
    "latitude": 48.71024,
    "longitude": -113.68924,
    "feet": 9220,
    "meters": 2810,
    "continent": "North America",
    "country": "United States",
    "state": "Montana"
  }
}
