{
  "type": "Feature",
  "geometry": {
    "type": "Point",
    "coordinates": [
      77.0666,
      10.1666
    ]
  },
  "properties": {
    "name": "Anamudi",
    "latitude": 10.1666,
    "longitude": 77.0666,
    "feet": 8842,
    "meters": 2695,
    "continent": "Asia",
    "country": "India",
    "marker-symbol": "triangle",
    "marker-size": "small"
  }
}
