{
  "type": "Feature",
  "geometry": {
    "type": "Point",
    "coordinates": [
      76.020584,
      33.98077
    ]
  },
  "properties": {
    "name": "Nun Kun",
    "latitude": 33.98077,
    "longitude": 76.020584,
    "feet": 23410,
    "meters": 7135,
    "continent": "Asia",
    "country": "India"
  }
}
