{
  "type": "Feature",
  "geometry": {
    "type": "Point",
    "coordinates": [
      -107.095893,
      35.598997
    ]
  },
  "properties": {
    "name": "Cabezon Peak",
    "latitude": 35.598997,
    "longitude": -107.095893,
    "feet": 7795,
    "meters": 2376,
    "continent": "North America",
    "country": "United States",
    "state": "New Mexico",
    "marker-symbol": "triangle",
    "marker-size": "small"
  }
}
