{
  "type": "Feature",
  "geometry": {
    "type": "Point",
    "coordinates": [
      -105.562228,
      36.054813
    ]
  },
  "properties": {
    "name": "Jicarita Peak",
    "latitude": 36.054813,
    "longitude": -105.562228,
    "feet": 12835,
    "meters": 3912,
    "continent": "North America",
    "country": "United States",
    "state": "New Mexico"
  }
}
