{
  "type": "Feature",
  "geometry": {
    "type": "Point",
    "coordinates": [
      7.833424,
      47.82301
    ]
  },
  "properties": {
    "name": "Belchen",
    "latitude": 47.82301,
    "longitude": 7.833424,
    "feet": 4639,
    "meters": 1414,
    "continent": "Europe",
    "country": "Germany"
  }
}
