{
  "type": "Feature",
  "geometry": {
    "type": "Point",
    "coordinates": [
      12.0225,
      65.4466
    ]
  },
  "properties": {
    "name": "Grytfoten",
    "latitude": 65.4466,
    "longitude": 12.0225,
    "feet": 3343,
    "meters": 1019,
    "continent": "Europe",
    "country": "Norway"
  }
}
