{
  "type": "Feature",
  "geometry": {
    "type": "Point",
    "coordinates": [
      12.0225,
      65.4466
    ]
  },
  "properties": {
    "name": "Tvillingene",
    "latitude": 65.4466,
    "longitude": 12.0225,
    "feet": 3215,
    "meters": 980,
    "continent": "Europe",
    "country": "Norway",
    "marker-symbol": "triangle",
    "marker-size": "small"
  }
}
