{
  "type": "Feature",
  "geometry": {
    "type": "Point",
    "coordinates": [
      -61.416667,
      10.733333
    ]
  },
  "properties": {
    "name": "El Tucuche",
    "latitude": 10.733333,
    "longitude": -61.416667,
    "feet": 3072,
    "meters": 936,
    "continent": "South America",
    "country": "Trinidad and Tobago"
  }
}
