{
  "type": "Feature",
  "geometry": {
    "type": "Point",
    "coordinates": [
      -124.776363,
      58.420775
    ]
  },
  "properties": {
    "name": "Cadet Mountain",
    "latitude": 58.420775,
    "longitude": -124.776363,
    "feet": 2340,
    "meters": 713,
    "continent": "North America",
    "country": "Canada"
  }
}
