{
  "type": "Feature",
  "geometry": {
    "type": "Point",
    "coordinates": [
      -114.574013,
      49.704944
    ]
  },
  "properties": {
    "name": "Crowsnest Mountain",
    "latitude": 49.704944,
    "longitude": -114.574013,
    "feet": 9137,
    "meters": 2785,
    "continent": "North America",
    "country": "Canada"
  }
}
