{
  "type": "Feature",
  "geometry": {
    "type": "Point",
    "coordinates": [
      -116.434307,
      51.62537
    ]
  },
  "properties": {
    "name": "Crowfoot Mountain",
    "latitude": 51.62537,
    "longitude": -116.434307,
    "feet": 10007,
    "meters": 3050,
    "continent": "North America",
    "country": "Canada"
  }
}
