{
  "type": "Feature",
  "geometry": {
    "type": "Point",
    "coordinates": [
      -116.375,
      51.675
    ]
  },
  "properties": {
    "name": "Dolomite Peak",
    "latitude": 51.675,
    "longitude": -116.375,
    "feet": 9127,
    "meters": 2782,
    "continent": "North America",
    "country": "Canada"
  }
}
