{
  "type": "Feature",
  "geometry": {
    "type": "Point",
    "coordinates": [
      -117.329779,
      52.041036
    ]
  },
  "properties": {
    "name": "Mount Bryce",
    "latitude": 52.041036,
    "longitude": -117.329779,
    "feet": 11506,
    "meters": 3507,
    "continent": "North America",
    "country": "Canada",
    "marker-symbol": "triangle",
    "marker-size": "small"
  }
}
