{
  "type": "Feature",
  "geometry": {
    "type": "Point",
    "coordinates": [
      -122.433,
      50.3167
    ]
  },
  "properties": {
    "name": "Mount Matier",
    "latitude": 50.3167,
    "longitude": -122.433,
    "feet": 9130,
    "meters": 2783,
    "continent": "North America",
    "country": "Canada"
  }
}
