{
  "type": "Feature",
  "geometry": {
    "type": "Point",
    "coordinates": [
      -115.293,
      50.7494
    ]
  },
  "properties": {
    "name": "Mount Murray",
    "latitude": 50.7494,
    "longitude": -115.293,
    "feet": 9928,
    "meters": 3026,
    "continent": "North America",
    "country": "Canada"
  }
}
