{
  "type": "Feature",
  "geometry": {
    "type": "Point",
    "coordinates": [
      -116.674805,
      51.93347
    ]
  },
  "properties": {
    "name": "Mount Murchison",
    "latitude": 51.93347,
    "longitude": -116.674805,
    "feet": 10935,
    "meters": 3333,
    "continent": "North America",
    "country": "Canada"
  }
}
