{
  "type": "Feature",
  "geometry": {
    "type": "Point",
    "coordinates": [
      -117.436209,
      52.14879
    ]
  },
  "properties": {
    "name": "Mount Columbia",
    "latitude": 52.14879,
    "longitude": -117.436209,
    "feet": 12294,
    "meters": 3747,
    "continent": "North America",
    "country": "Canada"
  }
}
