{
  "type": "Feature",
  "geometry": {
    "type": "Point",
    "coordinates": [
      -121.682056,
      49.186728
    ]
  },
  "properties": {
    "name": "Mount Cheam",
    "latitude": 49.186728,
    "longitude": -121.682056,
    "feet": 6903,
    "meters": 2104,
    "continent": "North America",
    "country": "Canada",
    "marker-symbol": "triangle",
    "marker-size": "small"
  }
}
