{
  "type": "Feature",
  "geometry": {
    "type": "Point",
    "coordinates": [
      -116.008,
      51.1569
    ]
  },
  "properties": {
    "name": "Mount Ball",
    "latitude": 51.1569,
    "longitude": -116.008,
    "feet": 10863,
    "meters": 3311,
    "continent": "North America",
    "country": "Canada",
    "marker-symbol": "triangle",
    "marker-size": "small"
  }
}
