{
  "type": "Feature",
  "geometry": {
    "type": "Point",
    "coordinates": [
      -122.6867,
      55.4567
    ]
  },
  "properties": {
    "name": "Mount Murray",
    "latitude": 55.4567,
    "longitude": -122.6867,
    "feet": 5968,
    "meters": 1819,
    "continent": "North America",
    "country": "Canada"
  }
}
