{
  "type": "Feature",
  "geometry": {
    "type": "Point",
    "coordinates": [
      -116.1014,
      51.2847
    ]
  },
  "properties": {
    "name": "Mount Bell",
    "latitude": 51.2847,
    "longitude": -116.1014,
    "feet": 9626,
    "meters": 2934,
    "continent": "North America",
    "country": "Canada"
  }
}
