{
  "type": "Feature",
  "geometry": {
    "type": "Point",
    "coordinates": [
      -116.228399,
      51.301616
    ]
  },
  "properties": {
    "name": "Mount Tuzo",
    "latitude": 51.301616,
    "longitude": -116.228399,
    "feet": 10650,
    "meters": 3246,
    "continent": "North America",
    "country": "Canada",
    "marker-symbol": "triangle",
    "marker-size": "small"
  }
}
