{
  "type": "Feature",
  "geometry": {
    "type": "Point",
    "coordinates": [
      -116.467,
      51.7333
    ]
  },
  "properties": {
    "name": "Observation Peak",
    "latitude": 51.7333,
    "longitude": -116.467,
    "feet": 10413,
    "meters": 3174,
    "continent": "North America",
    "country": "Canada"
  }
}
