{
  "type": "Feature",
  "geometry": {
    "type": "Point",
    "coordinates": [
      22.14,
      42.33
    ]
  },
  "properties": {
    "name": "Besna Kobila",
    "latitude": 42.33,
    "longitude": 22.14,
    "feet": 6309,
    "meters": 1923,
    "continent": "Europe",
    "country": "Serbia and Montenegro",
    "marker-symbol": "triangle",
    "marker-size": "small"
  }
}
