{
  "type": "Feature",
  "geometry": {
    "type": "Point",
    "coordinates": [
      8.08401,
      46.23837
    ]
  },
  "properties": {
    "name": "Breithorn (Simplon)",
    "latitude": 46.23837,
    "longitude": 8.08401,
    "feet": 11280,
    "meters": 3438,
    "continent": "Europe",
    "country": "Switzerland"
  }
}
