{
  "type": "Feature",
  "geometry": {
    "type": "Point",
    "coordinates": [
      7.26667,
      46.6167
    ]
  },
  "properties": {
    "name": "Chorblispitz",
    "latitude": 46.6167,
    "longitude": 7.26667,
    "feet": 6900,
    "meters": 2103,
    "continent": "Europe",
    "country": "Switzerland"
  }
}
