{
  "type": "Feature",
  "geometry": {
    "type": "Point",
    "coordinates": [
      7.61667,
      46.0333
    ]
  },
  "properties": {
    "name": "Dent Blanche",
    "latitude": 46.0333,
    "longitude": 7.61667,
    "feet": 14291,
    "meters": 4356,
    "continent": "Europe",
    "country": "Switzerland"
  }
}
