{
  "type": "Feature",
  "geometry": {
    "type": "Point",
    "coordinates": [
      8.415589,
      46.603281
    ]
  },
  "properties": {
    "name": "Hannibal Turm",
    "latitude": 46.603281,
    "longitude": 8.415589,
    "feet": 9455,
    "meters": 2882,
    "continent": "Europe",
    "country": "Switzerland"
  }
}
