{
  "type": "Feature",
  "geometry": {
    "type": "Point",
    "coordinates": [
      7.925833,
      46.413333
    ]
  },
  "properties": {
    "name": "Nesthorn",
    "latitude": 46.413333,
    "longitude": 7.925833,
    "feet": 12539,
    "meters": 3822,
    "continent": "Europe",
    "country": "Switzerland"
  }
}
