{
  "type": "Feature",
  "geometry": {
    "type": "Point",
    "coordinates": [
      7.58593,
      46.07258
    ]
  },
  "properties": {
    "name": "Pointes de Mourti",
    "latitude": 46.07258,
    "longitude": 7.58593,
    "feet": 11693,
    "meters": 3564,
    "continent": "Europe",
    "country": "Switzerland"
  }
}
