{
  "type": "Feature",
  "geometry": {
    "type": "Point",
    "coordinates": [
      7.948866,
      46.540739
    ]
  },
  "properties": {
    "name": "Silberhorn (Alps)",
    "latitude": 46.540739,
    "longitude": 7.948866,
    "feet": 12123,
    "meters": 3695,
    "continent": "Europe",
    "country": "Switzerland",
    "marker-symbol": "triangle",
    "marker-size": "small"
  }
}
