{
  "type": "Feature",
  "geometry": {
    "type": "Point",
    "coordinates": [
      -37.342529,
      65.992329
    ]
  },
  "properties": {
    "name": "Nanu Sax",
    "latitude": 65.992329,
    "longitude": -37.342529,
    "feet": 4757,
    "meters": 1450,
    "continent": "North America",
    "country": "Greenland"
  }
}
