{
  "type": "Feature",
  "geometry": {
    "type": "Point",
    "coordinates": [
      6.690459,
      45.770956
    ]
  },
  "properties": {
    "name": "Aguille de Roselette",
    "latitude": 45.770956,
    "longitude": 6.690459,
    "feet": 7822,
    "meters": 2384,
    "continent": "Europe",
    "country": "France",
    "marker-symbol": "triangle",
    "marker-size": "small"
  }
}
