{
  "type": "Feature",
  "geometry": {
    "type": "Point",
    "coordinates": [
      84.0851,
      28.7311
    ]
  },
  "properties": {
    "name": "Chulu (Far) East",
    "latitude": 28.7311,
    "longitude": 84.0851,
    "feet": 19879,
    "meters": 6059,
    "continent": "Asia",
    "country": "Nepal",
    "marker-symbol": "triangle",
    "marker-size": "small"
  }
}
