{
  "type": "Feature",
  "geometry": {
    "type": "Point",
    "coordinates": [
      -95.708891,
      43.460154
    ]
  },
  "properties": {
    "name": "Hawkeye Point",
    "latitude": 43.460154,
    "longitude": -95.708891,
    "feet": 1670,
    "meters": 509,
    "continent": "North America",
    "country": "United States",
    "state": "Iowa"
  }
}
