{
  "type": "Feature",
  "geometry": {
    "type": "Point",
    "coordinates": [
      84.3667,
      28.85
    ]
  },
  "properties": {
    "name": "Ratna Chuli",
    "latitude": 28.85,
    "longitude": 84.3667,
    "feet": 23080,
    "meters": 7035,
    "continent": "Asia",
    "country": "China/Nepal"
  }
}
