{
  "type": "Feature",
  "geometry": {
    "type": "Point",
    "coordinates": [
      -7.021079,
      31.574404
    ]
  },
  "properties": {
    "name": "Anghomar",
    "latitude": 31.574404,
    "longitude": -7.021079,
    "feet": 11844,
    "meters": 3610,
    "continent": "Africa",
    "country": "Morocco",
    "marker-symbol": "triangle",
    "marker-size": "small"
  }
}
