{
  "type": "Feature",
  "geometry": {
    "type": "Point",
    "coordinates": [
      -106.344,
      38.6656
    ]
  },
  "properties": {
    "name": "Chrysolite",
    "latitude": 38.6656,
    "longitude": -106.344,
    "feet": 12822,
    "meters": 3908,
    "continent": "North America",
    "country": "United States",
    "state": "Colorado"
  }
}
