{
  "type": "Feature",
  "geometry": {
    "type": "Point",
    "coordinates": [
      -105.492,
      37.5825
    ]
  },
  "properties": {
    "name": "Ellingwood Point",
    "latitude": 37.5825,
    "longitude": -105.492,
    "feet": 14042,
    "meters": 4280,
    "continent": "North America",
    "country": "United States",
    "state": "Colorado"
  }
}
