{
  "type": "Feature",
  "geometry": {
    "type": "Point",
    "coordinates": [
      -106.989,
      39.0708
    ]
  },
  "properties": {
    "name": "Maroon Bells",
    "latitude": 39.0708,
    "longitude": -106.989,
    "feet": 14156,
    "meters": 4315,
    "continent": "North America",
    "country": "United States",
    "state": "Colorado"
  }
}
