{
  "type": "Feature",
  "geometry": {
    "type": "Point",
    "coordinates": [
      -104.515,
      39.0717
    ]
  },
  "properties": {
    "name": "Monument Hill",
    "latitude": 39.0717,
    "longitude": -104.515,
    "feet": 7352,
    "meters": 2241,
    "continent": "North America",
    "country": "United States",
    "state": "Colorado"
  }
}
