{
  "type": "Feature",
  "geometry": {
    "type": "Point",
    "coordinates": [
      -106.479,
      39.4681
    ]
  },
  "properties": {
    "name": "Mount of the Holy Cross",
    "latitude": 39.4681,
    "longitude": -106.479,
    "feet": 14005,
    "meters": 4269,
    "continent": "North America",
    "country": "United States",
    "state": "Colorado"
  }
}
