{
  "type": "Feature",
  "geometry": {
    "type": "Point",
    "coordinates": [
      -105.633,
      40.0883
    ]
  },
  "properties": {
    "name": "Mount Toll",
    "latitude": 40.0883,
    "longitude": -105.633,
    "feet": 12978,
    "meters": 3956,
    "continent": "North America",
    "country": "United States",
    "state": "Colorado",
    "marker-symbol": "triangle",
    "marker-size": "small"
  }
}
