{
  "type": "Feature",
  "geometry": {
    "type": "Point",
    "coordinates": [
      -105.616,
      40.0989
    ]
  },
  "properties": {
    "name": "Mount Audubon",
    "latitude": 40.0989,
    "longitude": -105.616,
    "feet": 13565,
    "meters": 4135,
    "continent": "North America",
    "country": "United States",
    "state": "Colorado",
    "marker-symbol": "triangle",
    "marker-size": "small"
  }
}
