{
  "type": "Feature",
  "geometry": {
    "type": "Point",
    "coordinates": [
      -105.668,
      39.5828
    ]
  },
  "properties": {
    "name": "Mount Bierstadt",
    "latitude": 39.5828,
    "longitude": -105.668,
    "feet": 14060,
    "meters": 4286,
    "continent": "North America",
    "country": "United States",
    "state": "Colorado",
    "marker-symbol": "triangle",
    "marker-size": "small"
  }
}
