{
  "type": "Feature",
  "geometry": {
    "type": "Point",
    "coordinates": [
      -105.643,
      39.5886
    ]
  },
  "properties": {
    "name": "Mount Evans",
    "latitude": 39.5886,
    "longitude": -105.643,
    "feet": 14264,
    "meters": 4350,
    "continent": "North America",
    "country": "United States",
    "state": "Colorado"
  }
}
