{
  "type": "Feature",
  "geometry": {
    "type": "Point",
    "coordinates": [
      -79.4833,
      39.2333
    ]
  },
  "properties": {
    "name": "Backbone Mountain",
    "latitude": 39.2333,
    "longitude": -79.4833,
    "feet": 3360,
    "meters": 1024,
    "continent": "North America",
    "country": "United States",
    "state": "Maryland"
  }
}
