{
  "type": "Feature",
  "geometry": {
    "type": "Point",
    "coordinates": [
      -78.8975,
      39.5814
    ]
  },
  "properties": {
    "name": "Dans Mountain",
    "latitude": 39.5814,
    "longitude": -78.8975,
    "feet": 2898,
    "meters": 883,
    "continent": "North America",
    "country": "United States",
    "state": "Maryland"
  }
}
