{
  "type": "Feature",
  "geometry": {
    "type": "Point",
    "coordinates": [
      -71.2308,
      -13.7881
    ]
  },
  "properties": {
    "name": "Ausangate",
    "latitude": -13.7881,
    "longitude": -71.2308,
    "feet": 20945,
    "meters": 6384,
    "continent": "South America",
    "country": "Peru",
    "marker-symbol": "triangle",
    "marker-size": "small"
  }
}
