{
  "type": "Feature",
  "geometry": {
    "type": "Point",
    "coordinates": [
      -72.1083,
      42.8611
    ]
  },
  "properties": {
    "name": "Mount Monadnock",
    "latitude": 42.8611,
    "longitude": -72.1083,
    "feet": 3165,
    "meters": 965,
    "continent": "North America",
    "country": "United States",
    "state": "New Hampshire"
  }
}
